service_allocation/__init__.py
service_allocation/service_allocation.py
service_allocation-0.0.2.dist-info/LICENSE
service_allocation-0.0.2.dist-info/METADATA
service_allocation-0.0.2.dist-info/WHEEL
service_allocation-0.0.2.dist-info/entry_points.txt
service_allocation-0.0.2.dist-info/top_level.txt
service_allocation-0.0.2.dist-info/RECORD
