Metadata-Version: 2.1
Name: service-allocation
Version: 0.0.2
Summary: 
Home-page: https://github.com/msmarcal/service_allocation
Author: Marcelo Subtil Marcal
Author-email: marcelo.marcal@canonical.com
License: MIT
Platform: any
Classifier: Development Status :: 3 - Alpha
Classifier: License :: OSI Approved :: GNU General Public License v3 (GPLv3)
Classifier: Programming Language :: Python :: 3
Classifier: Intended Audience :: System Administrators
Requires-Dist: PyYAML (==5.3.1)
